radio_code_calculator/__init__.py
radio_code_calculator/radio_code_calculator.py
radio_code_calculator-1.1.6.dist-info/METADATA
radio_code_calculator-1.1.6.dist-info/WHEEL
radio_code_calculator-1.1.6.dist-info/top_level.txt
radio_code_calculator-1.1.6.dist-info/RECORD
