Metadata-Version: 2.1
Name: radio-code-calculator
Version: 1.1.6
Summary: Radio Code Calculator is an online service along with Web API and SDK for generating car radio unlock codes for popular vehicle brands.
Home-page: https://www.pelock.com/products/radio-code-calculator
Author: Bartosz Wójcik
Author-email: support@pelock.com
License: Apache-2.0
Keywords: radio code navigation calculator generator vehicle car automotive radiocode radiocodes api
Platform: UNKNOWN
Classifier: Development Status :: 5 - Production/Stable
Classifier: Topic :: Software Development :: Libraries :: Python Modules
Classifier: Topic :: Security
Classifier: Topic :: Multimedia :: Sound/Audio
Classifier: Natural Language :: English
Classifier: License :: OSI Approved :: Apache Software License
Classifier: Programming Language :: Python :: 3
Requires-Dist: requests
